venvjail/__init__.py
venvjail/cli.py
venvjail/venvjail.py
venvjail-0.0.0.dist-info/AUTHORS.rst
venvjail-0.0.0.dist-info/LICENSE
venvjail-0.0.0.dist-info/METADATA
venvjail-0.0.0.dist-info/WHEEL
venvjail-0.0.0.dist-info/entry_points.txt
venvjail-0.0.0.dist-info/top_level.txt
venvjail-0.0.0.dist-info/RECORD
