Metadata-Version: 2.1
Name: venvjail
Version: 0.0.0
Summary: Python virtual environment which jails executed programs.
Home-page: https://github.com/wrr/venvjail
Author: Jan Wrobel
Author-email: jan@mixedbit.org
License: MIT license
Keywords: venvjail
Classifier: Development Status :: 1 - Planning
Classifier: Intended Audience :: Developers
Classifier: License :: OSI Approved :: MIT License
Classifier: Natural Language :: English
Classifier: Operating System :: POSIX :: Linux
Classifier: Programming Language :: Python :: 3
Requires-Python: >=3.8
License-File: LICENSE
License-File: AUTHORS.rst
